autochests_bot/__init__.py
autochests_bot/__main__.py
autochests_bot/start_bot.py
autochests_bot/bot_controll/__init__.py
autochests_bot/bot_controll/args.py
autochests_bot/bot_controll/chests_bot.py
twitch_chest_bot-0.9.2.dist-info/LICENSE
twitch_chest_bot-0.9.2.dist-info/METADATA
twitch_chest_bot-0.9.2.dist-info/WHEEL
twitch_chest_bot-0.9.2.dist-info/top_level.txt
twitch_chest_bot-0.9.2.dist-info/RECORD
