Metadata-Version: 2.1
Name: twitch-chest-bot
Version: 0.9.2
Summary: Twitch bot for auto collection of chests
Home-page: https://github.com/J4CKVVH173/twitch_auto_chests
Author: J4CK VVH173
Author-email: author@example.com
License: UNKNOWN
Platform: UNKNOWN
Classifier: Programming Language :: Python :: 3
Classifier: License :: OSI Approved :: MIT License
Classifier: Operating System :: Unix
Requires-Python: >=3.6
Requires-Dist: daemon-process
Requires-Dist: numpy (==1.18.1)
Requires-Dist: pynput (==1.6.6)
Requires-Dist: pyscreenshot (==0.6)
Requires-Dist: Pillow (==7.0.0)
